whisper_evaluate/__init__.py
whisper_evaluate/aio_query.py
whisper_evaluate/compares.py
whisper_evaluate/config.py
whisper_evaluate/netease_statistics.py
whisper_evaluate/report.py
whisper_evaluate/statistics.py
whisper_evaluate/utils.py
whisper_evaluate/whisper_statistics.py
whisper_evaluate-1.3.0.dist-info/METADATA
whisper_evaluate-1.3.0.dist-info/WHEEL
whisper_evaluate-1.3.0.dist-info/top_level.txt
whisper_evaluate-1.3.0.dist-info/RECORD
