Metadata-Version: 2.1
Name: whisper-evaluate
Version: 1.3.0
Summary: Evaluate the effectiveness of the Whisper model.
Home-page: https://git.xindong.com/fengyanglu/whisper-evaluate
Author: geb
Author-email: 853934146@qq.com
License: UNKNOWN
Platform: UNKNOWN
Classifier: Programming Language :: Python :: 3
Classifier: License :: OSI Approved :: MIT License
Classifier: Operating System :: OS Independent
Requires-Python: >=3.6
Requires-Dist: numpy
Requires-Dist: pandas
Requires-Dist: aiohttp
Requires-Dist: tqdm
Requires-Dist: pandarallel
Requires-Dist: requests
